{
  "hash": "b27136ef",
  "configHash": "81db84f3",
  "lockfileHash": "27aaa4c7",
  "browserHash": "622c523c",
  "optimized": {
    "vue": {
      "src": "../../../../node_modules/vue/dist/vue.runtime.esm-bundler.js",
      "file": "vue.js",
      "fileHash": "0f0da4fa",
      "needsInterop": false
    },
    "vitepress > @vue/devtools-api": {
      "src": "../../../../node_modules/@vue/devtools-api/dist/index.js",
      "file": "vitepress___@vue_devtools-api.js",
      "fileHash": "d28b0492",
      "needsInterop": false
    },
    "vitepress > @vueuse/core": {
      "src": "../../../../node_modules/vitepress/node_modules/@vueuse/core/index.mjs",
      "file": "vitepress___@vueuse_core.js",
      "fileHash": "1ae84d09",
      "needsInterop": false
    },
    "element-plus": {
      "src": "../../../../node_modules/element-plus/es/index.mjs",
      "file": "element-plus.js",
      "fileHash": "475f8bee",
      "needsInterop": false
    },
    "vue-demi": {
      "src": "../../../../node_modules/vitepress/lib/vue-demi.mjs",
      "file": "vue-demi.js",
      "fileHash": "18d20095",
      "needsInterop": false
    }
  },
  "chunks": {
    "chunk-ZDT2FX2F": {
      "file": "chunk-ZDT2FX2F.js"
    },
    "chunk-UMQQJOTV": {
      "file": "chunk-UMQQJOTV.js"
    },
    "chunk-G3PMV62Z": {
      "file": "chunk-G3PMV62Z.js"
    }
  }
}